LICENSE
MANIFEST.in
README.md
setup.cfg
setup.py
scurl/__init__.py
scurl/canonicalize.cpp
scurl/canonicalize.pyx
scurl/cgurl.cpp
scurl/cgurl.pyx
scurl/chromium_gurl.pxd
scurl/chromium_url_canon.pxd
scurl/chromium_url_canon_stdstring.pxd
scurl/chromium_url_constant.pxd
scurl/chromium_url_util.pxd
scurl/chromium_url_util_internal.pxd
scurl/mozilla_url_parse.pxd
scurl/scurl_canonicalize_helper.pxd
scurl.egg-info/PKG-INFO
scurl.egg-info/SOURCES.txt
scurl.egg-info/dependency_links.txt
scurl.egg-info/not-zip-safe
scurl.egg-info/requires.txt
scurl.egg-info/top_level.txt
tests/__init__.py
third_party/chromium/base/at_exit.cc
third_party/chromium/base/at_exit.h
third_party/chromium/base/at_exit_unittest.cc
third_party/chromium/base/atomic_ref_count.h
third_party/chromium/base/atomic_sequence_num.h
third_party/chromium/base/atomicops.h
third_party/chromium/base/atomicops_internals_atomicword_compat.h
third_party/chromium/base/atomicops_internals_portable.h
third_party/chromium/base/atomicops_internals_x86_msvc.h
third_party/chromium/base/atomicops_unittest.cc
third_party/chromium/base/auto_reset.h
third_party/chromium/base/barrier_closure.cc
third_party/chromium/base/barrier_closure.h
third_party/chromium/base/barrier_closure_unittest.cc
third_party/chromium/base/base64.cc
third_party/chromium/base/base64.h
third_party/chromium/base/base64_decode_fuzzer.cc
third_party/chromium/base/base64_encode_fuzzer.cc
third_party/chromium/base/base64_unittest.cc
third_party/chromium/base/base64url.cc
third_party/chromium/base/base64url.h
third_party/chromium/base/base64url_unittest.cc
third_party/chromium/base/base_export.h
third_party/chromium/base/base_paths.cc
third_party/chromium/base/base_paths.h
third_party/chromium/base/base_paths_android.cc
third_party/chromium/base/base_paths_android.h
third_party/chromium/base/base_paths_fuchsia.cc
third_party/chromium/base/base_paths_fuchsia.h
third_party/chromium/base/base_paths_mac.h
third_party/chromium/base/base_paths_posix.cc
third_party/chromium/base/base_paths_posix.h
third_party/chromium/base/base_paths_win.cc
third_party/chromium/base/base_paths_win.h
third_party/chromium/base/base_switches.cc
