Metadata-Version: 1.1
Name: scurl
Version: 0.1.0
Summary: UNKNOWN
Home-page: https://github.com/scrapy/scurl
Author: UNKNOWN
Author-email: UNKNOWN
License: Apache License, Version 2.0
Keywords: urlparse,urlsplit,urljoin,url,parser,urlparser,parsing,gurl,cython,faster,speed,performance
Platform: any
Classifier: Programming Language :: Python
Classifier: Programming Language :: Python :: 2
Classifier: Programming Language :: Python :: 2.7
Classifier: Programming Language :: Python :: 3.4
Classifier: Programming Language :: Python :: 3.5
Classifier: Programming Language :: Python :: 3.6
Classifier: Programming Language :: Python :: Implementation :: CPython
Classifier: Programming Language :: Python :: Implementation :: PyPy
Classifier: Intended Audience :: Developers
Classifier: License :: OSI Approved :: Apache Software License
Classifier: Operating System :: OS Independent
Classifier: Topic :: Software Development :: Libraries
